flixtimeutils/__init__.py
flixtimeutils/client_info.py
flixtimeutils/json_codable.py
flixtimeutils/url_builder.py
flixtimeutils/user_agent.py
flixtimeutils-0.0.10.dist-info/LICENSE
flixtimeutils-0.0.10.dist-info/METADATA
flixtimeutils-0.0.10.dist-info/WHEEL
flixtimeutils-0.0.10.dist-info/top_level.txt
flixtimeutils-0.0.10.dist-info/RECORD
